cast6ecb.cpython-39-darwin.so
cast6ecb-0.3.1.dist-info/METADATA
cast6ecb-0.3.1.dist-info/WHEEL
cast6ecb-0.3.1.dist-info/top_level.txt
cast6ecb-0.3.1.dist-info/RECORD
